{
    "architecture": "MIPS",
    "av_labels_generation_date": "2020-08-09T18:25:09",
    "avclass_labels": {
        "gafgyt": 14,
        "ircbot": 3,
        "mirai": 2
    },
    "elf_header_info": {
        "abi_version": 0,
        "class": "ELF32",
        "data": "2's complement, big endian",
        "entrypoint": 4194976,
        "hdr_version": "1 (current)",
        "num_prog_headers": 4,
        "num_section_headers": 21,
        "obj_version": "0x1",
        "os_abi": "UNIX - System V",
        "type": "EXEC (Executable file)"
    },
    "first_submission_date": "2018-07-18T21:58:39",
    "magic": "ELF 32-bit MSB executable, MIPS, MIPS-I version 1 (SYSV), statically linked, not stripped",
    "magic_is_stripped": false,
    "magic_linking": "static",
    "md5": "1424c04c2b24b2cb1eec67dac8d21114",
    "sha1": "fec3c27b37e933d71d6de9ff1e39e27b6f796e4f",
    "sha256": "238c554783be3d2bb8bf1fd6a990ab05dc086cd8a8f2496eb5d3698348edaf54",
    "size": 125480,
    "tlsh": "D5C3A62A3E11EFEFE5A987300BF34B7087D5259226A19785F26CDB1C5F6128C185F7A0"
}