{
    "architecture": "MIPS",
    "av_labels_generation_date": "2020-08-09T19:05:46",
    "avclass_labels": {
        "mirai": 12
    },
    "elf_header_info": {
        "abi_version": 0,
        "class": "ELF32",
        "data": "2's complement, little endian",
        "entrypoint": 1075328,
        "hdr_version": "1 (current)",
        "num_prog_headers": 2,
        "num_section_headers": 0,
        "obj_version": "0x1",
        "os_abi": "UNIX - System V",
        "type": "EXEC (Executable file)"
    },
    "first_submission_date": "2019-09-10T07:04:56",
    "magic": "ELF 32-bit LSB executable, MIPS, MIPS-I version 1 (SYSV), statically linked, stripped",
    "magic_is_stripped": true,
    "magic_linking": "static",
    "md5": "c47ec93ea6cb0de04ed51ecc4fec6783",
    "sha1": "0a0299b6b89a1a6b22b4e4ac8aff0422cd8439a8",
    "sha256": "254ecf266194429e53f9a1b06fac244b3b24ed1665f8dcf4e43b38c9a8aabaec",
    "size": 31968,
    "tlsh": "D7E2F19D58F83DAAEECE083E12DD0469ED9B645203599FD5236104C0AE1F829E5EC47C"
}