{
    "architecture": "MIPS",
    "av_labels_generation_date": "2020-08-04T13:48:35",
    "avclass_labels": {
        "ddos": 5,
        "gafgyt": 15,
        "lightaidra": 2,
        "mirai": 3
    },
    "elf_header_info": {
        "abi_version": 0,
        "class": "ELF32",
        "data": "2's complement, big endian",
        "entrypoint": 4194976,
        "hdr_version": "1 (current)",
        "num_prog_headers": 4,
        "num_section_headers": 21,
        "obj_version": "0x1",
        "os_abi": "UNIX - System V",
        "type": "EXEC (Executable file)"
    },
    "first_submission_date": "2019-04-11T13:38:33",
    "magic": "ELF 32-bit MSB executable, MIPS, MIPS-I version 1 (SYSV), statically linked, not stripped",
    "magic_is_stripped": false,
    "magic_linking": "static",
    "md5": "508b030edc438fe1d8f2557a59386758",
    "sha1": "860e9033f68efac9ee21bc8f11ac739ab3dbeede",
    "sha256": "347fe460a032c15e7365b9bf46b3a120b0ddde59d2f457b38eb0f7a071862668",
    "size": 181745,
    "tlsh": "000497AA3A606B7DE198877147F7AEB0C2A878D72A92D342D22DE6045F7034D1D5F370"
}