{
    "architecture": "MIPS",
    "av_labels_generation_date": "2020-08-05T04:11:29",
    "avclass_labels": {
        "mirai": 18
    },
    "elf_header_info": {
        "abi_version": 0,
        "class": "ELF32",
        "data": "2's complement, big endian",
        "entrypoint": 4194912,
        "hdr_version": "1 (current)",
        "num_prog_headers": 3,
        "num_section_headers": 13,
        "obj_version": "0x1",
        "os_abi": "UNIX - System V",
        "type": "EXEC (Executable file)"
    },
    "first_submission_date": "2019-07-26T17:32:23",
    "magic": "ELF 32-bit MSB executable, MIPS, MIPS-I version 1 (SYSV), statically linked, stripped",
    "magic_is_stripped": true,
    "magic_linking": "static",
    "md5": "0d8c8c7f2beab4245060575e608201a6",
    "sha1": "61f926f8c88d0a14c12c7e3533fa3d6039b2d613",
    "sha256": "4772195fe4f4eb5f67b4c9fc46cd262f9ef19622161930e139fc94ac26a078fc",
    "size": 68472,
    "tlsh": "2563851A3E218FBEFBAC863847B74A21565833D622F1D5C4E15CEE015E6038E745FB98"
}