{
    "architecture": "MIPS",
    "av_labels_generation_date": "2020-08-07T12:23:10",
    "avclass_labels": {
        "mirai": 23
    },
    "elf_header_info": {
        "abi_version": 0,
        "class": "ELF32",
        "data": "2's complement, little endian",
        "entrypoint": 4194912,
        "hdr_version": "1 (current)",
        "num_prog_headers": 3,
        "num_section_headers": 13,
        "obj_version": "0x1",
        "os_abi": "UNIX - System V",
        "type": "EXEC (Executable file)"
    },
    "first_submission_date": "2019-05-11T11:14:25",
    "magic": "ELF 32-bit LSB executable, MIPS, MIPS-I version 1 (SYSV), statically linked, stripped",
    "magic_is_stripped": true,
    "magic_linking": "static",
    "md5": "4b2f91c636fdfe9001139742ae7cd045",
    "sha1": "d7982f1f297a95938095748b37eabf06c81a0467",
    "sha256": "5380c02c111a14e97a7d44d85dda61c5013271bcbb0f0096d8421a39a2a100cc",
    "size": 92100,
    "tlsh": "7693800AAF611FF7E89EDC374AD92B0524DD511A20AD7B39B930D818F25B30F19E3865"
}