{
    "architecture": "MIPS",
    "av_labels_generation_date": "2020-08-08T02:18:12",
    "avclass_labels": {
        "ddos": 3,
        "gafgyt": 14,
        "mirai": 2
    },
    "elf_header_info": {
        "abi_version": 0,
        "class": "ELF32",
        "data": "2's complement, little endian",
        "entrypoint": 4194976,
        "hdr_version": "1 (current)",
        "num_prog_headers": 4,
        "num_section_headers": 20,
        "obj_version": "0x1",
        "os_abi": "UNIX - System V",
        "type": "EXEC (Executable file)"
    },
    "first_submission_date": "2019-08-01T10:20:04",
    "magic": "ELF 32-bit LSB executable, MIPS, MIPS-I version 1 (SYSV), statically linked, not stripped",
    "magic_is_stripped": false,
    "magic_linking": "static",
    "md5": "0a8098806cbb45e3fd0b0da6487664f5",
    "sha1": "872c5c52deb718dc6f6c9f00409dc3303f6454f4",
    "sha256": "5ef13c191d333ffd62a57b924bcf1510b5ffe8e3a2d143506529496184200a48",
    "size": 104664,
    "tlsh": "91A3E817BB51DEB7C85FCE7306AA460120CEE55612A46B6FB2B4DA2CE74794F08E3D40"
}