{
    "architecture": "MIPS",
    "av_labels_generation_date": "2020-08-10T11:08:02",
    "avclass_labels": {
        "mirai": 25
    },
    "elf_header_info": {
        "abi_version": 0,
        "class": "ELF32",
        "data": "2's complement, little endian",
        "entrypoint": 4194912,
        "hdr_version": "1 (current)",
        "num_prog_headers": 3,
        "num_section_headers": 14,
        "obj_version": "0x1",
        "os_abi": "UNIX - System V",
        "type": "EXEC (Executable file)"
    },
    "first_submission_date": "2019-07-30T02:53:19",
    "magic": "ELF 32-bit LSB executable, MIPS, MIPS-I version 1 (SYSV), statically linked, stripped",
    "magic_is_stripped": true,
    "magic_linking": "static",
    "md5": "792a2e99d71474e96768293e764f5b7a",
    "sha1": "2cc14757fa0da98316e686756eda33bbefbfaea5",
    "sha256": "81d4e42ea55fb8f499394d76a9c3c77e7bc98d7887dd58e90d598136c4520b6a",
    "size": 92056,
    "tlsh": "DF93A40AAF611FF7F89FDC7759D92B05249D101A60993B79B930D818F24B25F19E38B0"
}