{
    "architecture": "MIPS",
    "av_labels_generation_date": "2020-08-07T10:11:07",
    "avclass_labels": {
        "mirai": 20
    },
    "elf_header_info": {
        "abi_version": 0,
        "class": "ELF32",
        "data": "2's complement, little endian",
        "entrypoint": 4194912,
        "hdr_version": "1 (current)",
        "num_prog_headers": 3,
        "num_section_headers": 14,
        "obj_version": "0x1",
        "os_abi": "UNIX - System V",
        "type": "EXEC (Executable file)"
    },
    "first_submission_date": "2019-09-08T16:16:23",
    "magic": "ELF 32-bit LSB executable, MIPS, MIPS-I version 1 (SYSV), statically linked, stripped",
    "magic_is_stripped": true,
    "magic_linking": "static",
    "md5": "57450e22848a8d5e9ed9485cee970b6f",
    "sha1": "b779b386aa402dc29082f7b73f0d51dbaa5e3de7",
    "sha256": "9c36aaeac5cec5125a94d8fb17713d2f0dcd56934c7c7266cfcb3ffa5cc58016",
    "size": 88472,
    "tlsh": "7483A309AF715FFBE86FDD3705E9170628CD550A22A93B75B970D828F34A24F09E3864"
}