{
    "architecture": "MIPS",
    "av_labels_generation_date": "2020-08-04T17:31:00",
    "avclass_labels": {
        "mirai": 22
    },
    "elf_header_info": {
        "abi_version": 0,
        "class": "ELF32",
        "data": "2's complement, big endian",
        "entrypoint": 4194912,
        "hdr_version": "1 (current)",
        "num_prog_headers": 3,
        "num_section_headers": 13,
        "obj_version": "0x1",
        "os_abi": "UNIX - System V",
        "type": "EXEC (Executable file)"
    },
    "first_submission_date": "2018-04-07T05:52:10",
    "magic": "ELF 32-bit MSB executable, MIPS, MIPS-I version 1 (SYSV), statically linked, stripped",
    "magic_is_stripped": true,
    "magic_linking": "static",
    "md5": "ed33f929a711514da2a8e44348a82063",
    "sha1": "fe7d86ce852b657cc1d9646a2a4e05e42d9a8b3e",
    "sha256": "d4da102ce45f21c033b1452a51426e68b5814eba6536420631cf5c484477eed8",
    "size": 69416,
    "tlsh": "0C63960A3E218FBEFBAC863847B74A219658339626F1C5C5E15CEE015E7034E745FB98"
}