{
    "architecture": "MIPS",
    "av_labels_generation_date": "2020-08-07T15:22:43",
    "avclass_labels": {
        "mirai": 13
    },
    "elf_header_info": {
        "abi_version": 0,
        "class": "ELF32",
        "data": "2's complement, little endian",
        "entrypoint": 1075328,
        "hdr_version": "1 (current)",
        "num_prog_headers": 2,
        "num_section_headers": 0,
        "obj_version": "0x1",
        "os_abi": "UNIX - System V",
        "type": "EXEC (Executable file)"
    },
    "first_submission_date": "2019-07-25T19:06:08",
    "magic": "ELF 32-bit LSB executable, MIPS, MIPS-I version 1 (SYSV), statically linked, stripped",
    "magic_is_stripped": true,
    "magic_linking": "static",
    "md5": "c815c543656da80e7fa3e86878bd7c7b",
    "sha1": "971c7c589288d02cecbd690ded331f646cb658fc",
    "sha256": "ed91c15ca2af3012bfb34a1b3ea00c8a67b406c6bfe2e83bfef98020c20de1ab",
    "size": 31968,
    "tlsh": "7BE2E14D64A83DEAEFCA4C3D52DD0919ED5B58A64319DFCA232248C09D2F829E1DC47D"
}