{
    "architecture": "MIPS",
    "av_labels_generation_date": "2020-08-06T01:28:39",
    "avclass_labels": {
        "mirai": 18
    },
    "elf_header_info": {
        "abi_version": 0,
        "class": "ELF32",
        "data": "2's complement, little endian",
        "entrypoint": 4194912,
        "hdr_version": "1 (current)",
        "num_prog_headers": 3,
        "num_section_headers": 13,
        "obj_version": "0x1",
        "os_abi": "UNIX - System V",
        "type": "EXEC (Executable file)"
    },
    "first_submission_date": "2019-05-31T13:28:16",
    "magic": "ELF 32-bit LSB executable, MIPS, MIPS-I version 1 (SYSV), statically linked, stripped",
    "magic_is_stripped": true,
    "magic_linking": "static",
    "md5": "3c154cfc43436b3a20ef6644acf0f8e2",
    "sha1": "a1edadf52d6bb1181ff67d4cfe3a3b2aa66141f2",
    "sha256": "ef413cc249118eb330e999ffbd4d5e557221086f3d1a94c1576133f8e45a6126",
    "size": 59504,
    "tlsh": "49436109BF650EB7EC6BDC370AE91B4535CC641B61A93B297934D818F20B65B09E3CB4"
}