{
    "architecture": "ARM",
    "av_labels_generation_date": "2020-08-07T08:28:48",
    "avclass_labels": {
        "gafgyt": 16
    },
    "elf_header_info": {
        "abi_version": 0,
        "class": "ELF32",
        "data": "2's complement, little endian",
        "entrypoint": 33168,
        "hdr_version": "1 (current)",
        "num_prog_headers": 3,
        "num_section_headers": 20,
        "obj_version": "0x1",
        "os_abi": "ARM",
        "type": "EXEC (Executable file)"
    },
    "first_submission_date": "2019-06-15T06:32:13",
    "magic": "ELF 32-bit LSB executable, ARM, version 1, statically linked, not stripped",
    "magic_is_stripped": false,
    "magic_linking": "static",
    "md5": "963cf061f503dca8029d6cdd46072546",
    "sha1": "d22cb92eefb658479737ed5febcf858587a44153",
    "sha256": "077b911d06a1aea09d4866c46a2eb90e4045c0c006910be68b55edade542892e",
    "size": 116040,
    "tlsh": "6DB30905F9404B23C6D26BBBF79B43CD77366658ABD7330196297EB02BC17982E3A150"
}