{
    "architecture": "ARM",
    "av_labels_generation_date": "2020-08-05T22:10:27",
    "avclass_labels": {
        "mirai": 12
    },
    "elf_header_info": {
        "abi_version": 0,
        "class": "ELF32",
        "data": "2's complement, little endian",
        "entrypoint": 62368,
        "hdr_version": "1 (current)",
        "num_prog_headers": 3,
        "num_section_headers": 0,
        "obj_version": "0x1",
        "os_abi": "UNIX - Linux",
        "type": "EXEC (Executable file)"
    },
    "first_submission_date": "2019-05-26T12:04:30",
    "magic": "ELF 32-bit LSB executable, ARM, version 1 (GNU/Linux), statically linked, stripped",
    "magic_is_stripped": true,
    "magic_linking": "static",
    "md5": "7b1a9284059d0cfe2ccd5b6b7b9fe4e4",
    "sha1": "b43c7b2a8e4c93692744b90c2b3ddfce519d37d4",
    "sha256": "0b1e655bcda3d432bf726290a13c2791fbc8807a7b0f7bfd446a2149de1ebaae",
    "size": 34488,
    "tlsh": "3FF2E16325598D71CFF0357AE6D0A2017FA85E7CD2A478B251501F14B7CF98FA5A028F"
}