{
    "architecture": "ARM",
    "av_labels_generation_date": "2020-08-07T13:32:16",
    "avclass_labels": {
        "mirai": 13
    },
    "elf_header_info": {
        "abi_version": 0,
        "class": "ELF32",
        "data": "2's complement, little endian",
        "entrypoint": 66880,
        "hdr_version": "1 (current)",
        "num_prog_headers": 3,
        "num_section_headers": 0,
        "obj_version": "0x1",
        "os_abi": "UNIX - Linux",
        "type": "EXEC (Executable file)"
    },
    "first_submission_date": "2019-06-29T16:50:21",
    "magic": "ELF 32-bit LSB executable, ARM, version 1 (GNU/Linux), statically linked, stripped",
    "magic_is_stripped": true,
    "magic_linking": "static",
    "md5": "398af5ec8dec3df98155c9d417de7da7",
    "sha1": "ab5e19f40236505b997da975fad9ea6838d79d7c",
    "sha256": "124e78d12ea63fbbfecf8394018ac0e7b3f0dcdb1d30a3fc2dd7db7b31c2dd61",
    "size": 53636,
    "tlsh": "7833F152B2321FB2AC798877F5B401466AD88BBC61CAF7734248CA8C4562F4BF05E4D3"
}