{
    "architecture": "ARM",
    "av_labels_generation_date": "2020-08-08T16:23:56",
    "avclass_labels": {
        "mirai": 20
    },
    "elf_header_info": {
        "abi_version": 0,
        "class": "ELF32",
        "data": "2's complement, little endian",
        "entrypoint": 33168,
        "hdr_version": "1 (current)",
        "num_prog_headers": 3,
        "num_section_headers": 10,
        "obj_version": "0x1",
        "os_abi": "ARM",
        "type": "EXEC (Executable file)"
    },
    "first_submission_date": "2018-03-12T03:44:00",
    "magic": "ELF 32-bit LSB executable, ARM, version 1, statically linked, stripped",
    "magic_is_stripped": true,
    "magic_linking": "static",
    "md5": "e19f98671caf330e6d72e52ddb839b44",
    "sha1": "25cb6e808751932ab311f92dcada3c65f3e3a2f7",
    "sha256": "13f8eef11253aeb7d387c34b7e1f5d05629378a0e468f91bad04e4f6e56d6a80",
    "size": 56880,
    "tlsh": "A94308817881A626C7D05377FA5F018D33199798E0EE33578C296FA07B8AD1F0D6B74A"
}