{
    "architecture": "ARM",
    "av_labels_generation_date": "2020-08-10T09:06:47",
    "avclass_labels": {
        "mirai": 19
    },
    "elf_header_info": {
        "abi_version": 0,
        "class": "ELF32",
        "data": "2's complement, little endian",
        "entrypoint": 33172,
        "hdr_version": "1 (current)",
        "num_prog_headers": 5,
        "num_section_headers": 29,
        "obj_version": "0x1",
        "os_abi": "UNIX - System V",
        "type": "EXEC (Executable file)"
    },
    "first_submission_date": "2018-07-14T17:04:48",
    "magic": "ELF 32-bit LSB executable, ARM, version 1 (SYSV), statically linked, not stripped",
    "magic_is_stripped": false,
    "magic_linking": "static",
    "md5": "6eaccd76384111072cdf3ef75edd7221",
    "sha1": "352655344abacc0c7fba93fcd16f597ab69dabfa",
    "sha256": "169bd9bd66acb3d204f1e0fe1b0c6d96a03d3faf9e5e6ced784418f0887bd963",
    "size": 128063,
    "tlsh": "F4C32B46EA409B13C5D617B7FAAF41493322DB54D3DB330689285BF43F87A9E0D27A06"
}