{
    "architecture": "ARM",
    "av_labels_generation_date": "2020-08-09T04:09:06",
    "avclass_labels": {
        "mirai": 12
    },
    "elf_header_info": {
        "abi_version": 0,
        "class": "ELF32",
        "data": "2's complement, little endian",
        "entrypoint": 53008,
        "hdr_version": "1 (current)",
        "num_prog_headers": 3,
        "num_section_headers": 0,
        "obj_version": "0x1",
        "os_abi": "ARM",
        "type": "EXEC (Executable file)"
    },
    "first_submission_date": "2019-02-06T08:51:21",
    "magic": "ELF 32-bit LSB executable, ARM, version 1, statically linked, stripped",
    "magic_is_stripped": true,
    "magic_linking": "static",
    "md5": "8fec23a7b23fdc970b70b06e96317924",
    "sha1": "863304ad53223266690cd2ad072a506cecb68605",
    "sha256": "276ec36cde22e11db6599be7b0b95bbdc1c828ddcff747ede8b6d00b3eb13d54",
    "size": 25004,
    "tlsh": "C2B2E1327286F8B2C2B10634DB8AD547F7E24DFCD1F12319205521ACA6D970685F97C7"
}