{
    "architecture": "ARM",
    "av_labels_generation_date": "2020-08-10T06:12:57",
    "avclass_labels": {
        "mirai": 24
    },
    "elf_header_info": {
        "abi_version": 0,
        "class": "ELF32",
        "data": "2's complement, little endian",
        "entrypoint": 33168,
        "hdr_version": "1 (current)",
        "num_prog_headers": 3,
        "num_section_headers": 10,
        "obj_version": "0x1",
        "os_abi": "ARM",
        "type": "EXEC (Executable file)"
    },
    "first_submission_date": "2019-05-25T21:36:20",
    "magic": "ELF 32-bit LSB executable, ARM, version 1, statically linked, stripped",
    "magic_is_stripped": true,
    "magic_linking": "static",
    "md5": "a7a8f74daf13b81fe1c2a0cac7cc4cc0",
    "sha1": "6c6cc826a434deac1a91c15045842c2ef101966f",
    "sha256": "2c6903aa49de08cf5f017e954523b1e6b809a6bb4775934bc857372446568446",
    "size": 70468,
    "tlsh": "F0632981B880AA26C7C01777FA5F118E3315A7DCE1EA73438C156FA576CAC1F0D6B64A"
}