{
    "architecture": "ARM",
    "av_labels_generation_date": "2020-08-10T11:08:27",
    "avclass_labels": {
        "mirai": 19
    },
    "elf_header_info": {
        "abi_version": 0,
        "class": "ELF32",
        "data": "2's complement, little endian",
        "entrypoint": 33108,
        "hdr_version": "1 (current)",
        "num_prog_headers": 3,
        "num_section_headers": 12,
        "obj_version": "0x1",
        "os_abi": "UNIX - System V",
        "type": "EXEC (Executable file)"
    },
    "first_submission_date": "2018-07-26T22:50:38",
    "magic": "ELF 32-bit LSB executable, ARM, version 1 (SYSV), statically linked, stripped",
    "magic_is_stripped": true,
    "magic_linking": "static",
    "md5": "2eeccbec112c75548dd9ced136674389",
    "sha1": "d9ea89c8479ae4e025daa77cd2428883bb48389c",
    "sha256": "37d2401e804fda7093953b67b75169307fc9c95cafa63c1cfd7bddcd480f530a",
    "size": 70992,
    "tlsh": "E1631A8178819A15C6D516BBFE1F018D331257ACE2EE7312CD145F647B8B92F0E3BA1A"
}