{
    "architecture": "ARM",
    "av_labels_generation_date": "2020-08-05T18:09:14",
    "avclass_labels": {
        "tsunami": 20
    },
    "elf_header_info": {
        "abi_version": 0,
        "class": "ELF32",
        "data": "2's complement, little endian",
        "entrypoint": 33168,
        "hdr_version": "1 (current)",
        "num_prog_headers": 3,
        "num_section_headers": 20,
        "obj_version": "0x1",
        "os_abi": "ARM",
        "type": "EXEC (Executable file)"
    },
    "first_submission_date": "2018-03-30T07:02:16",
    "magic": "ELF 32-bit LSB executable, ARM, version 1, statically linked, not stripped",
    "magic_is_stripped": false,
    "magic_linking": "static",
    "md5": "ca9cbe25993965ddd8057f1f3bf48723",
    "sha1": "05c264b9485ca284fe9697e9dc918c8e32b3a023",
    "sha256": "3f5340d682f125466fbf685d1499c2678b4d0c8224dfab75873af3ec2c4fece3",
    "size": 94160,
    "tlsh": "3A933B85F9118767C2D23BBBFB8F435C7B366A1497973311762C6EB42B82B8D1E25210"
}