{
    "architecture": "ARM",
    "av_labels_generation_date": "2020-08-07T14:13:49",
    "avclass_labels": {
        "mirai": 24
    },
    "elf_header_info": {
        "abi_version": 0,
        "class": "ELF32",
        "data": "2's complement, little endian",
        "entrypoint": 33108,
        "hdr_version": "1 (current)",
        "num_prog_headers": 3,
        "num_section_headers": 12,
        "obj_version": "0x1",
        "os_abi": "UNIX - System V",
        "type": "EXEC (Executable file)"
    },
    "first_submission_date": "2019-07-24T07:30:15",
    "magic": "ELF 32-bit LSB executable, ARM, version 1 (SYSV), statically linked, stripped",
    "magic_is_stripped": true,
    "magic_linking": "static",
    "md5": "05e728fb3891f6fbe174f4fc0f2dca80",
    "sha1": "9c5f22dea399416729309f440e55c4cea29b4802",
    "sha256": "3ff14301e2f8044e26c7e6de0a3cb768d1b57580e34fe98b0d6a0c4757ff1489",
    "size": 74880,
    "tlsh": "7A731986B8419A21C6C516B7FE2F104E330297A8E2EE7353DD145F6477CB85F0E2B91A"
}