{
    "architecture": "ARM",
    "av_labels_generation_date": "2020-08-09T11:07:31",
    "avclass_labels": {
        "mirai": 19
    },
    "elf_header_info": {
        "abi_version": 0,
        "class": "ELF32",
        "data": "2's complement, little endian",
        "entrypoint": 33108,
        "hdr_version": "1 (current)",
        "num_prog_headers": 3,
        "num_section_headers": 12,
        "obj_version": "0x1",
        "os_abi": "UNIX - System V",
        "type": "EXEC (Executable file)"
    },
    "first_submission_date": "2019-07-09T09:02:49",
    "magic": "ELF 32-bit LSB executable, ARM, version 1 (SYSV), statically linked, stripped",
    "magic_is_stripped": true,
    "magic_linking": "static",
    "md5": "4853c91a5423393b67064305915302f0",
    "sha1": "08a122b3190d1ddbd763fd159a08d020705cd734",
    "sha256": "430fe74c1a59a0d4d09f35b5e4aec36b7068a0127b314043e6c43e93031fd2a7",
    "size": 66892,
    "tlsh": "B663F846BC818F15C8D812BAFA2E118D331367A8E2DFB3269D106F147BC792B0E77655"
}