{
    "architecture": "ARM",
    "av_labels_generation_date": "2020-08-09T23:10:03",
    "avclass_labels": {
        "mirai": 21
    },
    "elf_header_info": {
        "abi_version": 0,
        "class": "ELF32",
        "data": "2's complement, little endian",
        "entrypoint": 33168,
        "hdr_version": "1 (current)",
        "num_prog_headers": 3,
        "num_section_headers": 10,
        "obj_version": "0x1",
        "os_abi": "ARM",
        "type": "EXEC (Executable file)"
    },
    "first_submission_date": "2018-07-04T19:18:23",
    "magic": "ELF 32-bit LSB executable, ARM, version 1, statically linked, stripped",
    "magic_is_stripped": true,
    "magic_linking": "static",
    "md5": "585470551fbe46d5188a6d5850714d52",
    "sha1": "0989b1cbf4fb63536b00fbf5b72f4ed27c2312a9",
    "sha256": "5772082933ab621459293c80a045aeee33242535f1146bdf8a6028adbfe81831",
    "size": 56880,
    "tlsh": "DE4308817881A626C7D05377FA5F018D33199798E0EE33578C296FA07B8AD1F0D6B74A"
}