{
    "architecture": "ARM",
    "av_labels_generation_date": "2020-08-08T09:20:23",
    "avclass_labels": {
        "mirai": 13
    },
    "elf_header_info": {
        "abi_version": 0,
        "class": "ELF32",
        "data": "2's complement, little endian",
        "entrypoint": 57536,
        "hdr_version": "1 (current)",
        "num_prog_headers": 3,
        "num_section_headers": 0,
        "obj_version": "0x1",
        "os_abi": "ARM",
        "type": "EXEC (Executable file)"
    },
    "first_submission_date": "2018-04-02T20:04:49",
    "magic": "ELF 32-bit LSB executable, ARM, version 1, statically linked, stripped",
    "magic_is_stripped": true,
    "magic_linking": "static",
    "md5": "973932fe4b14b926b99d9c4f3827a9da",
    "sha1": "279b201f40d5675178fa7da4c226094bc4d57194",
    "sha256": "5c41562e8a8a9277fa816ac938594c67ad51658f02f98ebf90b6d0aafe3e4b4a",
    "size": 29532,
    "tlsh": "9DD2D1D118A9FD96C2304436FE3DDA873A7397B6F1D7A7524A50407EDA8A10D10B6353"
}