{
    "architecture": "ARM",
    "av_labels_generation_date": "2020-08-07T07:46:40",
    "avclass_labels": {
        "mirai": 19
    },
    "elf_header_info": {
        "abi_version": 0,
        "class": "ELF32",
        "data": "2's complement, little endian",
        "entrypoint": 36492,
        "hdr_version": "1 (current)",
        "num_prog_headers": 6,
        "num_section_headers": 18,
        "obj_version": "0x1",
        "os_abi": "ARM",
        "type": "EXEC (Executable file)"
    },
    "first_submission_date": "2019-01-20T02:59:08",
    "magic": "ELF 32-bit LSB executable, ARM, version 1, dynamically linked (uses shared libs), stripped",
    "magic_is_stripped": true,
    "magic_linking": "dynamic (uses shared libs)",
    "md5": "4994c8e1391b7dfcca408c9ad8b73001",
    "sha1": "b1fd3c2a1648fa6a6680a8234fc6816c9c3a1570",
    "sha256": "5cce5283befff9e1a38e4d5b687d775345acd9a88d50567610fd790cba048250",
    "size": 42880,
    "tlsh": "6C13F796BC829A66C6E0237BFA5F418D3321A3E8D1DF3257CC112B057AC991F0DA7B41"
}