{
    "architecture": "ARM",
    "av_labels_generation_date": "2020-08-07T19:26:00",
    "avclass_labels": {
        "ddos": 3,
        "gafgyt": 14,
        "lightaidra": 2,
        "mirai": 2
    },
    "elf_header_info": {
        "abi_version": 0,
        "class": "ELF32",
        "data": "2's complement, little endian",
        "entrypoint": 33200,
        "hdr_version": "1 (current)",
        "num_prog_headers": 4,
        "num_section_headers": 24,
        "obj_version": "0x1",
        "os_abi": "UNIX - System V",
        "type": "EXEC (Executable file)"
    },
    "first_submission_date": "2019-01-01T07:34:17",
    "magic": "ELF 32-bit LSB executable, ARM, version 1 (SYSV), statically linked, not stripped",
    "magic_is_stripped": false,
    "magic_linking": "static",
    "md5": "fe5d630d29f4a0e95b4ac46fd21abe74",
    "sha1": "33b7c757e60120b006c9fb8657655e171d311ee8",
    "sha256": "633718863d7533e5bb899e7c68be45ad7f22aaeb22b4080c517dde363ead174f",
    "size": 164214,
    "tlsh": "81F32A06E4504663C2D22BB6B35B524D77231FB997CB3311D9287EB02FE1B9E1A399D0"
}