{
    "architecture": "ARM",
    "av_labels_generation_date": "2020-08-06T03:27:14",
    "avclass_labels": {
        "mirai": 12
    },
    "elf_header_info": {
        "abi_version": 0,
        "class": "ELF32",
        "data": "2's complement, little endian",
        "entrypoint": 62368,
        "hdr_version": "1 (current)",
        "num_prog_headers": 3,
        "num_section_headers": 0,
        "obj_version": "0x1",
        "os_abi": "UNIX - Linux",
        "type": "EXEC (Executable file)"
    },
    "first_submission_date": "2019-05-25T02:56:49",
    "magic": "ELF 32-bit LSB executable, ARM, version 1 (GNU/Linux), statically linked, stripped",
    "magic_is_stripped": true,
    "magic_linking": "static",
    "md5": "02eb27d0fc0b6717f899669382e5e57a",
    "sha1": "4ec44558d8213706194e0a6ec67559ff19f2f494",
    "sha256": "663171e255b416d7e8e73721c8ad8acf287cbb541da356e4a5226e6e574a0807",
    "size": 34488,
    "tlsh": "4EF2E063695ACD61CFF0313AE6D17241BFA91A38C16474B651616F18BBCFD8F70A028B"
}