{
    "architecture": "ARM",
    "av_labels_generation_date": "2020-08-05T01:16:42",
    "avclass_labels": {
        "mirai": 22
    },
    "elf_header_info": {
        "abi_version": 0,
        "class": "ELF32",
        "data": "2's complement, little endian",
        "entrypoint": 36560,
        "hdr_version": "1 (current)",
        "num_prog_headers": 6,
        "num_section_headers": 18,
        "obj_version": "0x1",
        "os_abi": "ARM",
        "type": "EXEC (Executable file)"
    },
    "first_submission_date": "2018-11-13T08:21:39",
    "magic": "ELF 32-bit LSB executable, ARM, version 1, dynamically linked (uses shared libs), stripped",
    "magic_is_stripped": true,
    "magic_linking": "dynamic (uses shared libs)",
    "md5": "a545032838f9014d4f6a64267b57dc04",
    "sha1": "9814f6815de20c8e0e0eebe68178aa3e066d6e75",
    "sha256": "74ab21c702d695ef06c8fab9dc5faaba9f2f33129579a40c00988f1468edffd8",
    "size": 54508,
    "tlsh": "1A332A86FC96862AC6C0237ABB2E119D332173D8C2DF72079D141B2477CA51E5E77792"
}