{
    "architecture": "ARM",
    "av_labels_generation_date": "2020-08-10T03:06:58",
    "avclass_labels": {
        "mirai": 18
    },
    "elf_header_info": {
        "abi_version": 0,
        "class": "ELF32",
        "data": "2's complement, little endian",
        "entrypoint": 33108,
        "hdr_version": "1 (current)",
        "num_prog_headers": 3,
        "num_section_headers": 12,
        "obj_version": "0x1",
        "os_abi": "UNIX - System V",
        "type": "EXEC (Executable file)"
    },
    "first_submission_date": "2019-05-17T20:46:54",
    "magic": "ELF 32-bit LSB executable, ARM, version 1 (SYSV), statically linked, stripped",
    "magic_is_stripped": true,
    "magic_linking": "static",
    "md5": "099d86d32aed511a7f500beaeb73835b",
    "sha1": "ff3c13b9e414ed619c6d8505d04701ad7abb8c00",
    "sha256": "7c72dc7564e265e2e5eab7bbe2ccaeae04c329c4e0ea4d8ef6dcd4e3d8d6b663",
    "size": 59204,
    "tlsh": "E9431856B8818A15C5D412BAFE2E118D3317676CE3DFB2139D106F247BCA92F0E7B912"
}