{
    "architecture": "ARM",
    "av_labels_generation_date": "2020-08-05T20:28:46",
    "avclass_labels": {
        "mirai": 12
    },
    "elf_header_info": {
        "abi_version": 0,
        "class": "ELF32",
        "data": "2's complement, little endian",
        "entrypoint": 57960,
        "hdr_version": "1 (current)",
        "num_prog_headers": 3,
        "num_section_headers": 0,
        "obj_version": "0x1",
        "os_abi": "ARM",
        "type": "EXEC (Executable file)"
    },
    "first_submission_date": "2019-07-21T22:39:37",
    "magic": "ELF 32-bit LSB executable, ARM, version 1, statically linked, stripped",
    "magic_is_stripped": true,
    "magic_linking": "static",
    "md5": "dd3ffd1018c47ef79f0c0be87513d368",
    "sha1": "f9d923c11d605d33ee08e6cdb0bd1ab35c04baf7",
    "sha256": "8d4c175f1370c6a0d882aba076cee350ef760e4fd41bfde071adc5fc24f381fc",
    "size": 29960,
    "tlsh": "3DD2E154B7A1E8B0DEB4533EEE7C8142225B13FBE4DCB5DB16948919B24C60BD339286"
}