{
    "architecture": "ARM",
    "av_labels_generation_date": "2020-08-05T22:10:55",
    "avclass_labels": {
        "mirai": 13
    },
    "elf_header_info": {
        "abi_version": 0,
        "class": "ELF32",
        "data": "2's complement, little endian",
        "entrypoint": 61872,
        "hdr_version": "1 (current)",
        "num_prog_headers": 3,
        "num_section_headers": 0,
        "obj_version": "0x1",
        "os_abi": "UNIX - Linux",
        "type": "EXEC (Executable file)"
    },
    "first_submission_date": "2018-12-29T23:25:21",
    "magic": "ELF 32-bit LSB executable, ARM, version 1 (GNU/Linux), statically linked, stripped",
    "magic_is_stripped": true,
    "magic_linking": "static",
    "md5": "fc901b16f0d7e6e0e2034bfb3934ab12",
    "sha1": "0197e4c729340676de88d8e1a00a54e199e87725",
    "sha256": "8d9b30c9216570b619ceac4788ab2a7b5034c065a8be1088e5f3b2524caf686d",
    "size": 48572,
    "tlsh": "4023F1A3AE915527D7FA2BF6C7F087B1769A74BC70E63122022458E09A7944D3F350BC"
}