{
    "architecture": "ARM",
    "av_labels_generation_date": "2020-08-04T16:07:35",
    "avclass_labels": {
        "ddos": 3,
        "gafgyt": 14,
        "lightaidra": 2,
        "mirai": 2
    },
    "elf_header_info": {
        "abi_version": 0,
        "class": "ELF32",
        "data": "2's complement, little endian",
        "entrypoint": 33200,
        "hdr_version": "1 (current)",
        "num_prog_headers": 4,
        "num_section_headers": 24,
        "obj_version": "0x1",
        "os_abi": "UNIX - System V",
        "type": "EXEC (Executable file)"
    },
    "first_submission_date": "2017-02-09T09:23:54",
    "magic": "ELF 32-bit LSB executable, ARM, version 1 (SYSV), statically linked, not stripped",
    "magic_is_stripped": false,
    "magic_linking": "static",
    "md5": "f4ea2718cd44bb44fb42ca9c6949e2b6",
    "sha1": "149188980fb97effb58a87c8c88ced9988500642",
    "sha256": "a6ab146b7a36822e38f8e4fe5c4b1dfc5b3551a282a88ed689d344fa9c2f051a",
    "size": 139738,
    "tlsh": "07D33B05F8505A27CBD22B7FF7AA528E77226B98A7C7331146296FF42BC179C1E39110"
}