{
    "architecture": "ARM",
    "av_labels_generation_date": "2020-08-07T09:18:14",
    "avclass_labels": {
        "mirai": 14
    },
    "elf_header_info": {
        "abi_version": 0,
        "class": "ELF32",
        "data": "2's complement, little endian",
        "entrypoint": 54160,
        "hdr_version": "1 (current)",
        "num_prog_headers": 3,
        "num_section_headers": 0,
        "obj_version": "0x1",
        "os_abi": "ARM",
        "type": "EXEC (Executable file)"
    },
    "first_submission_date": "2018-09-03T03:42:13",
    "magic": "ELF 32-bit LSB executable, ARM, version 1, statically linked, stripped",
    "magic_is_stripped": true,
    "magic_linking": "static",
    "md5": "46571a557d8d9291a34b62943488cab3",
    "sha1": "bdf6c154bb99bbc9f9973854e8c4964254a1a9d7",
    "sha256": "a97feefa59a4e0bc22fe31cf14ce0ac0bf8f30fa7af34cad2c2c40e4fdbd30f0",
    "size": 26292,
    "tlsh": "70C2E0741414B970D370053DFFADCA879B63D1F082E4311519542AFEA60B986B8BB78F"
}