{
    "architecture": "ARM",
    "av_labels_generation_date": "2020-08-10T03:14:43",
    "avclass_labels": {
        "tsunami": 20
    },
    "elf_header_info": {
        "abi_version": 0,
        "class": "ELF32",
        "data": "2's complement, little endian",
        "entrypoint": 33200,
        "hdr_version": "1 (current)",
        "num_prog_headers": 4,
        "num_section_headers": 24,
        "obj_version": "0x1",
        "os_abi": "UNIX - System V",
        "type": "EXEC (Executable file)"
    },
    "first_submission_date": "2018-11-25T01:04:23",
    "magic": "ELF 32-bit LSB executable, ARM, version 1 (SYSV), statically linked, not stripped",
    "magic_is_stripped": false,
    "magic_linking": "static",
    "md5": "437c33c717aa7164041a7e48d24d88d1",
    "sha1": "676b930f808017c1da46fc98c8277e90cf44e3cd",
    "sha256": "acccae2354e036d02aea80c49634ae60f528126b21c147c53b1f89c148d5d9b5",
    "size": 116327,
    "tlsh": "EAB33905D5518667C1D227BAFB9F825E73222B68D38B3321762C7FB42F81B9D1E39121"
}