{
    "architecture": "ARM",
    "av_labels_generation_date": "2020-08-08T23:16:49",
    "avclass_labels": {
        "gafgyt": 2,
        "mirai": 19
    },
    "elf_header_info": {
        "abi_version": 0,
        "class": "ELF32",
        "data": "2's complement, little endian",
        "entrypoint": 33172,
        "hdr_version": "1 (current)",
        "num_prog_headers": 5,
        "num_section_headers": 29,
        "obj_version": "0x1",
        "os_abi": "UNIX - System V",
        "type": "EXEC (Executable file)"
    },
    "first_submission_date": "2018-10-11T02:11:04",
    "magic": "ELF 32-bit LSB executable, ARM, version 1 (SYSV), statically linked, not stripped",
    "magic_is_stripped": false,
    "magic_linking": "static",
    "md5": "48f37397b223fca58276c8e49709cf3d",
    "sha1": "3281a96b9c95337eafcf75fa3a09e8e93b180e35",
    "sha256": "b23a643a8bccbb9348f1b60ac6b74798f8de5e1d5ca98e64bafd13b99406a657",
    "size": 140592,
    "tlsh": "B2D35C46EA818F13C0D5277ABAAF42453322A754D3DB33069D189FB43F86BAE4E77501"
}