{
    "architecture": "ARM",
    "av_labels_generation_date": "2020-08-05T01:39:23",
    "avclass_labels": {
        "mirai": 17
    },
    "elf_header_info": {
        "abi_version": 0,
        "class": "ELF32",
        "data": "2's complement, little endian",
        "entrypoint": 33108,
        "hdr_version": "1 (current)",
        "num_prog_headers": 3,
        "num_section_headers": 12,
        "obj_version": "0x1",
        "os_abi": "UNIX - System V",
        "type": "EXEC (Executable file)"
    },
    "first_submission_date": "2018-09-17T19:25:26",
    "magic": "ELF 32-bit LSB executable, ARM, version 1 (SYSV), statically linked, stripped",
    "magic_is_stripped": true,
    "magic_linking": "static",
    "md5": "69efc2101d0a72e189ca2cd00185d7b5",
    "sha1": "6fd0ab436019ab4b104727019b8e68eafd558fe7",
    "sha256": "c1a5f21ccdce633326ae108d5a8a8116b0616e23866e567b79f27312ac907c11",
    "size": 66692,
    "tlsh": "0D53E856BC918A02C5D413BAFE2E118D33136378E2DFB3628D105F646BCA92F0E7B556"
}