{
    "architecture": "ARM",
    "av_labels_generation_date": "2020-08-07T17:08:55",
    "avclass_labels": {
        "mirai": 20
    },
    "elf_header_info": {
        "abi_version": 0,
        "class": "ELF32",
        "data": "2's complement, little endian",
        "entrypoint": 33172,
        "hdr_version": "1 (current)",
        "num_prog_headers": 5,
        "num_section_headers": 29,
        "obj_version": "0x1",
        "os_abi": "UNIX - System V",
        "type": "EXEC (Executable file)"
    },
    "first_submission_date": "2018-10-15T16:58:47",
    "magic": "ELF 32-bit LSB executable, ARM, version 1 (SYSV), statically linked, not stripped",
    "magic_is_stripped": false,
    "magic_linking": "static",
    "md5": "d6f4aab2ac8a12acd2d7e174abbc0df9",
    "sha1": "d1174845748ef3123c5e2957f6415bbb02a457ec",
    "sha256": "d27f460d53d9c702d947b435049cb8b6d16191b237ad1cc3f9494c2dfae0a56b",
    "size": 122176,
    "tlsh": "7EC33A4AFB808F13C4E51B7AB5AF425933229794D3DB730789189BF43F8666E0E63605"
}