{
    "architecture": "ARM",
    "av_labels_generation_date": "2020-08-08T04:15:02",
    "avclass_labels": {
        "mirai": 13
    },
    "elf_header_info": {
        "abi_version": 0,
        "class": "ELF32",
        "data": "2's complement, little endian",
        "entrypoint": 63320,
        "hdr_version": "1 (current)",
        "num_prog_headers": 3,
        "num_section_headers": 0,
        "obj_version": "0x1",
        "os_abi": "UNIX - Linux",
        "type": "EXEC (Executable file)"
    },
    "first_submission_date": "2018-11-09T02:46:09",
    "magic": "ELF 32-bit LSB executable, ARM, version 1 (GNU/Linux), statically linked, stripped",
    "magic_is_stripped": true,
    "magic_linking": "static",
    "md5": "568e4252a12a86393eea8a1973785806",
    "sha1": "7dcd7fc8d347cd8cd7737598d0bac992c4dc8bbe",
    "sha256": "d89c368d74b36301f067c9cedf108f78332693a9937380cf9ef3d88dc3d3c51c",
    "size": 35448,
    "tlsh": "96F2F1119BF524F1C17239747A7C8B9C5E122EFE52F7343A13049BAD0D8A203AA59AC3"
}