{
    "architecture": "ARM",
    "av_labels_generation_date": "2020-08-09T15:32:21",
    "avclass_labels": {
        "mirai": 13
    },
    "elf_header_info": {
        "abi_version": 0,
        "class": "ELF32",
        "data": "2's complement, little endian",
        "entrypoint": 57960,
        "hdr_version": "1 (current)",
        "num_prog_headers": 3,
        "num_section_headers": 0,
        "obj_version": "0x1",
        "os_abi": "ARM",
        "type": "EXEC (Executable file)"
    },
    "first_submission_date": "2019-06-29T16:50:35",
    "magic": "ELF 32-bit LSB executable, ARM, version 1, statically linked, stripped",
    "magic_is_stripped": true,
    "magic_linking": "static",
    "md5": "1c1f0dfaea9b62ac507b823a52bced69",
    "sha1": "bc88d7cd127a248aab800cb615d5067c6c810363",
    "sha256": "f44b89261fc5cc15d0ee29d2e3b9855ebaa9c3a9c68c1a2c71297b70190dd35c",
    "size": 29960,
    "tlsh": "D1D2E050A7E1E8B0DE74533EFE7C4142231713BBE4D8F5EB51988949B68C50BE339686"
}